elangai/__about__.py
elangai/__init__.py
elangai/__main__.py
elangai/_constant.py
elangai/_tensor.py
elangai/version.txt
elangai/callback/__init__.py
elangai/callback/_callback.py
elangai/inference/__init__.py
elangai/inference/_instance.py
elangai/interface/__init__.py
elangai/interface/_interface.py
elangai/logger/__init__.py
elangai/logger/_core.py
elangai/logger/logger.py
elangai/model/__init__.py
elangai/model/chainer.py
elangai/model/converter.py
elangai/model/core.py
elangai/model/dissector.py
elangai/template/__init__.py
elangai/template/_handler.py
elangai/template/_utils.py
elangai/template/app_name/config.json-tpl
elangai/template/app_name/main.py-tpl
elangai/template/app_name/utils/__init__.py-tpl
elangai/template/app_name/utils/postprocessing.py-tpl
elangai/template/app_name/utils/preprocessing.py-tpl
elangai/utils/__init__.py
elangai/utils/_constant.py
elangai/utils/_logging.py
elangai/utils/_timer.py
elangai/utils/exception.py
elangai-1.0.0.dist-info/LICENSE
elangai-1.0.0.dist-info/METADATA
elangai-1.0.0.dist-info/WHEEL
elangai-1.0.0.dist-info/entry_points.txt
elangai-1.0.0.dist-info/top_level.txt
elangai-1.0.0.dist-info/RECORD
