Metadata-Version: 2.1
Name: elangai
Version: 1.0.0
Summary: Inference Engine Platform on Edge Device.
Home-page: https://www.elang.ai/
Author: elangai Developer
Author-email: resha.alfahsi@techbros.io
License: UNKNOWN
Platform: UNKNOWN
Classifier: Development Status :: 5 - Production/Stable
Classifier: Intended Audience :: Developers
Classifier: License :: Other/Proprietary License
Classifier: Topic :: Scientific/Engineering :: Artificial Intelligence
Classifier: Topic :: Software Development :: Libraries :: Application Frameworks
Classifier: Programming Language :: Python :: 3.6
Requires-Dist: typer
